crma_api_client/__init__.py
crma_api_client/client.py
crma_api_client/encoder.py
crma_api_client/py.typed
crma_api_client/resources/__init__.py
crma_api_client/resources/dataset.py
crma_api_client/resources/query.py
crma_api_client/resources/user.py
crma_api_client/resources/util.py
crma_api_client-0.9.0.dist-info/LICENSE.md
crma_api_client-0.9.0.dist-info/WHEEL
crma_api_client-0.9.0.dist-info/METADATA
crma_api_client-0.9.0.dist-info/RECORD
