Metadata-Version: 2.1
Name: crma-api-client
Version: 0.9.0
Summary: CRM Analytics REST API Client
Home-page: https://github.com/NarrativeScience/crma-api-client
License: BSD-3-Clause
Author: Jonathan Drake
Author-email: jon.drake@salesforce.com
Requires-Python: >=3.9,<4.0
Classifier: License :: OSI Approved :: BSD License
Classifier: Programming Language :: Python :: 3
Classifier: Programming Language :: Python :: 3.10
Classifier: Programming Language :: Python :: 3.9
Requires-Dist: backoff (>=1.11.1,<2.0.0)
Requires-Dist: httpx (>=0.22,<0.24)
Requires-Dist: pydantic (>=1.9.0,<2.0.0)
Project-URL: Repository, https://github.com/NarrativeScience/crma-api-client
